{
  "installed": {
    "client_id": "581930412554-khdp5ovhbcpahm9fm9552mud69q9jb0l.apps.googleusercontent.com",
    "project_id": "line-bot-ae7b4",
    "auth_uri": "https://accounts.google.com/o/oauth2/auth",
    "token_uri": "https://oauth2.googleapis.com/token",
    "auth_provider_x509_cert_url": "https://www.googleapis.com/oauth2/v1/certs",
    "client_secret": "BxBa2Gw8XtMYIko11zUOHz_B",
    "redirect_uris": [
      "https://line-bot-ae7b4.firebaseapp.com/__/auth/handler",
      "http://localhost:5000"
    ],
    "javascript_origins": ["http://localhost", "http://localhost:5000"]
  }
}
